aiohasupervisor/__init__.py
aiohasupervisor/addons.py
aiohasupervisor/backups.py
aiohasupervisor/client.py
aiohasupervisor/const.py
aiohasupervisor/discovery.py
aiohasupervisor/exceptions.py
aiohasupervisor/homeassistant.py
aiohasupervisor/host.py
aiohasupervisor/jobs.py
aiohasupervisor/mounts.py
aiohasupervisor/network.py
aiohasupervisor/os.py
aiohasupervisor/py.typed
aiohasupervisor/resolution.py
aiohasupervisor/root.py
aiohasupervisor/store.py
aiohasupervisor/supervisor.py
aiohasupervisor/models/__init__.py
aiohasupervisor/models/addons.py
aiohasupervisor/models/backups.py
aiohasupervisor/models/base.py
aiohasupervisor/models/discovery.py
aiohasupervisor/models/homeassistant.py
aiohasupervisor/models/host.py
aiohasupervisor/models/jobs.py
aiohasupervisor/models/mounts.py
aiohasupervisor/models/network.py
aiohasupervisor/models/os.py
aiohasupervisor/models/resolution.py
aiohasupervisor/models/root.py
aiohasupervisor/models/supervisor.py
aiohasupervisor/utils/__init__.py
aiohasupervisor/utils/aiohttp.py
aiohasupervisor-0.3.3.dist-info/licenses/LICENSE
aiohasupervisor-0.3.3.dist-info/METADATA
aiohasupervisor-0.3.3.dist-info/WHEEL
aiohasupervisor-0.3.3.dist-info/top_level.txt
aiohasupervisor-0.3.3.dist-info/RECORD
