Metadata-Version: 2.4
Name: aiohasupervisor
Version: 0.3.3
Summary: Asynchronous python client for Home Assistant Supervisor.
Author-email: The Home Assistant Authors <hello@home-assistant.io>
License: Apache-2.0
Project-URL: Homepage, https://www.home-assistant.io/
Project-URL: Source Code, https://github.com/home-assistant-libs/python-supervisor-client
Project-URL: Bug Reports, https://github.com/home-assistant-libs/python-supervisor-client/issues
Project-URL: Docs: Dev, https://developers.home-assistant.io/
Project-URL: Discord, https://www.home-assistant.io/join-chat/
Project-URL: Forum, https://community.home-assistant.io/
Keywords: docker,home-assistant,api,client-library
Platform: any
Requires-Python: >=3.12.0
License-File: LICENSE
Requires-Dist: aiohttp<4.0.0,>=3.3.0
Requires-Dist: mashumaro<4.0,>=3.11
Requires-Dist: orjson<4.0.0,>=3.6.1
Provides-Extra: dev
Requires-Dist: aiohttp==3.12.15; extra == "dev"
Requires-Dist: mashumaro==3.16; extra == "dev"
Requires-Dist: orjson==3.11.3; extra == "dev"
Requires-Dist: aioresponses==0.7.8; extra == "dev"
Requires-Dist: codespell==2.4.1; extra == "dev"
Requires-Dist: coverage==7.10.7; extra == "dev"
Requires-Dist: mypy==1.18.2; extra == "dev"
Requires-Dist: pre-commit==4.3.0; extra == "dev"
Requires-Dist: pytest-aiohttp==1.1.0; extra == "dev"
Requires-Dist: pytest-cov==7.0.0; extra == "dev"
Requires-Dist: pytest-timeout==2.4.0; extra == "dev"
Requires-Dist: pytest==8.4.2; extra == "dev"
Requires-Dist: ruff==0.13.2; extra == "dev"
Requires-Dist: yamllint==1.37.1; extra == "dev"
Dynamic: license-file
